saiuncli/__init__.py
saiuncli/_constants.py
saiuncli/_utils.py
saiuncli/argument.py
saiuncli/cli.py
saiuncli/command.py
saiuncli/console.py
saiuncli/option.py
saiuncli/theme.py
saiuncli-0.1.11.dist-info/licenses/LICENSE
saiuncli-0.1.11.dist-info/METADATA
saiuncli-0.1.11.dist-info/WHEEL
saiuncli-0.1.11.dist-info/top_level.txt
saiuncli-0.1.11.dist-info/RECORD
