Metadata-Version: 2.4
Name: SaiunCLI
Version: 0.1.11
Summary: A Python framework for making CLI tools prettier and customizable.
Author-email: Erick Benitez-Ramos <erickbenitez336@gmail.com>
License: MIT
Project-URL: homepage, https://github.com/Erickkbentz/SaiunCLI
Project-URL: repository, https://github.com/Erickkbentz/SaiunCLI
Keywords: cli,framework,rich,customizable
Classifier: Development Status :: 3 - Alpha
Classifier: Intended Audience :: Developers
Classifier: License :: OSI Approved :: MIT License
Classifier: Programming Language :: Python :: 3
Classifier: Programming Language :: Python :: 3.7
Classifier: Programming Language :: Python :: 3.8
Classifier: Programming Language :: Python :: 3.9
Classifier: Programming Language :: Python :: 3.10
Requires-Python: >=3.7
License-File: LICENSE
Requires-Dist: rich<14,>=13.0
Provides-Extra: dev
Requires-Dist: pytest<8,>=7.0; extra == "dev"
Requires-Dist: black<23,>=22.0; extra == "dev"
Requires-Dist: flake8; extra == "dev"
Requires-Dist: build; extra == "dev"
Requires-Dist: twine; extra == "dev"
Provides-Extra: docs
Requires-Dist: mkdocs-material; extra == "docs"
Requires-Dist: mkdocstrings-python; extra == "docs"
Provides-Extra: all
Requires-Dist: rich<14,>=13.0; extra == "all"
Requires-Dist: pytest<8,>=7.0; extra == "all"
Requires-Dist: black<23,>=22.0; extra == "all"
Requires-Dist: flake8; extra == "all"
Requires-Dist: build; extra == "all"
Requires-Dist: twine; extra == "all"
Requires-Dist: mkdocs-material; extra == "all"
Requires-Dist: mkdocstrings-python; extra == "all"
Dynamic: license-file
